odoo/addons/website_portal_contact/README.rst
odoo/addons/website_portal_contact/__init__.py
odoo/addons/website_portal_contact/__manifest__.py
odoo/addons/website_portal_contact/controllers/__init__.py
odoo/addons/website_portal_contact/controllers/main.py
odoo/addons/website_portal_contact/i18n/ar.po
odoo/addons/website_portal_contact/i18n/bs.po
odoo/addons/website_portal_contact/i18n/ca.po
odoo/addons/website_portal_contact/i18n/cs.po
odoo/addons/website_portal_contact/i18n/da.po
odoo/addons/website_portal_contact/i18n/de.po
odoo/addons/website_portal_contact/i18n/el.po
odoo/addons/website_portal_contact/i18n/el_GR.po
odoo/addons/website_portal_contact/i18n/en_GB.po
odoo/addons/website_portal_contact/i18n/es.po
odoo/addons/website_portal_contact/i18n/es_AR.po
odoo/addons/website_portal_contact/i18n/es_CR.po
odoo/addons/website_portal_contact/i18n/es_EC.po
odoo/addons/website_portal_contact/i18n/es_MX.po
odoo/addons/website_portal_contact/i18n/es_VE.po
odoo/addons/website_portal_contact/i18n/et.po
odoo/addons/website_portal_contact/i18n/eu.po
odoo/addons/website_portal_contact/i18n/fi.po
odoo/addons/website_portal_contact/i18n/fr.po
odoo/addons/website_portal_contact/i18n/fr_CA.po
odoo/addons/website_portal_contact/i18n/gl.po
odoo/addons/website_portal_contact/i18n/hr.po
odoo/addons/website_portal_contact/i18n/hr_HR.po
odoo/addons/website_portal_contact/i18n/hu.po
odoo/addons/website_portal_contact/i18n/id.po
odoo/addons/website_portal_contact/i18n/it.po
odoo/addons/website_portal_contact/i18n/ja.po
odoo/addons/website_portal_contact/i18n/lt.po
odoo/addons/website_portal_contact/i18n/lv.po
odoo/addons/website_portal_contact/i18n/mk.po
odoo/addons/website_portal_contact/i18n/mn.po
odoo/addons/website_portal_contact/i18n/nb.po
odoo/addons/website_portal_contact/i18n/nl.po
odoo/addons/website_portal_contact/i18n/nl_BE.po
odoo/addons/website_portal_contact/i18n/nl_NL.po
odoo/addons/website_portal_contact/i18n/pl.po
odoo/addons/website_portal_contact/i18n/pt.po
odoo12_addon_website_portal_contact-12.0.1.0.0.99.dev11.dist-info/METADATA
odoo12_addon_website_portal_contact-12.0.1.0.0.99.dev11.dist-info/WHEEL
odoo12_addon_website_portal_contact-12.0.1.0.0.99.dev11.dist-info/top_level.txt
odoo12_addon_website_portal_contact-12.0.1.0.0.99.dev11.dist-info/RECORD
